[{"id":"cmkn0y94f0011fa9okdheekz7","level":"L0","code":"wmn","name":"WOMEN","slug":"women","parentId":null,"manufacturingGroup":null,"defaultShippingProfile":null,"defaultSizeProfileId":null,"isActive":true,"createdAt":"2026-01-20 20:06:17.007","updatedAt":"2026-01-20 20:07:27.33"},{"id":"cmkn1043y0013fa9o5opoxbia","level":"L0","code":"Men","name":"MEN","slug":"men","parentId":null,"manufacturingGroup":null,"defaultShippingProfile":null,"defaultSizeProfileId":null,"isActive":true,"createdAt":"2026-01-20 20:07:43.822","updatedAt":"2026-01-20 20:07:43.822"},{"id":"cmkn10bhd0015fa9omtib53wt","level":"L0","code":"KDS","name":"KIDS","slug":"kids","parentId":null,"manufacturingGroup":null,"defaultShippingProfile":null,"defaultSizeProfileId":null,"isActive":true,"createdAt":"2026-01-20 20:07:53.377","updatedAt":"2026-01-20 20:07:53.377"},{"id":"cmkn113120017fa9ozk1r0mzh","level":"L1","code":"APR","name":"Apparel","slug":"apparel","parentId":"cmkn0y94f0011fa9okdheekz7","manufacturingGroup":null,"defaultShippingProfile":null,"defaultSizeProfileId":null,"isActive":true,"createdAt":"2026-01-20 20:08:29.079","updatedAt":"2026-01-20 20:10:17.242"},{"id":"cmkn11jfm0019fa9ohfetm6cj","level":"L1","code":"OUT","name":"Outerwear","slug":"outerwear","parentId":"cmkn0y94f0011fa9okdheekz7","manufacturingGroup":null,"defaultShippingProfile":null,"defaultSizeProfileId":null,"isActive":true,"createdAt":"2026-01-20 20:08:50.338","updatedAt":"2026-01-20 20:08:50.338"},{"id":"cmkn11svh001bfa9o93hg5b1p","level":"L1","code":"KNT","name":"Knitwear","slug":"knitwear","parentId":"cmkn0y94f0011fa9okdheekz7","manufacturingGroup":null,"defaultShippingProfile":null,"defaultSizeProfileId":null,"isActive":true,"createdAt":"2026-01-20 20:09:02.574","updatedAt":"2026-01-20 20:10:09.065"},{"id":"cmkn122ny001dfa9oskogqp3l","level":"L1","code":"DNM","name":"Denim","slug":"denim","parentId":"cmkn0y94f0011fa9okdheekz7","manufacturingGroup":null,"defaultShippingProfile":null,"defaultSizeProfileId":null,"isActive":true,"createdAt":"2026-01-20 20:09:15.263","updatedAt":"2026-01-20 20:09:15.263"},{"id":"cmkn12bxh001ffa9o4fiqgf9g","level":"L1","code":"LTH","name":"Leather","slug":"leather","parentId":"cmkn0y94f0011fa9okdheekz7","manufacturingGroup":null,"defaultShippingProfile":null,"defaultSizeProfileId":null,"isActive":true,"createdAt":"2026-01-20 20:09:27.27","updatedAt":"2026-01-20 20:09:27.27"},{"id":"cmkn12ls1001hfa9ojunltzqb","level":"L1","code":"BAG","name":"Bags","slug":"bags","parentId":"cmkn0y94f0011fa9okdheekz7","manufacturingGroup":null,"defaultShippingProfile":null,"defaultSizeProfileId":null,"isActive":true,"createdAt":"2026-01-20 20:09:40.033","updatedAt":"2026-01-20 20:09:40.033"},{"id":"cmkn12xrj001jfa9ohp7o8urw","level":"L1","code":"SHO","name":"Shoes","slug":"shoes","parentId":"cmkn0y94f0011fa9okdheekz7","manufacturingGroup":null,"defaultShippingProfile":null,"defaultSizeProfileId":null,"isActive":true,"createdAt":"2026-01-20 20:09:55.568","updatedAt":"2026-01-20 20:09:55.568"},{"id":"cmkn13pdg001lfa9ovryf3nt8","level":"L1","code":"ACC","name":"Accessories","slug":"accessories","parentId":"cmkn0y94f0011fa9okdheekz7","manufacturingGroup":null,"defaultShippingProfile":null,"defaultSizeProfileId":null,"isActive":true,"createdAt":"2026-01-20 20:10:31.348","updatedAt":"2026-01-20 20:10:31.348"},{"id":"cmkn14bzx001nfa9oj5xpaawo","level":"L1","code":"FOC","name":"Formal & Occasion","slug":"formal-occasion","parentId":"cmkn0y94f0011fa9okdheekz7","manufacturingGroup":null,"defaultShippingProfile":null,"defaultSizeProfileId":null,"isActive":true,"createdAt":"2026-01-20 20:11:00.669","updatedAt":"2026-01-20 20:11:00.669"},{"id":"cmkn14pdu001pfa9otiivzn1x","level":"L2","code":"TOP","name":"Tops","slug":"tops","parentId":"cmkn113120017fa9ozk1r0mzh","manufacturingGroup":null,"defaultShippingProfile":null,"defaultSizeProfileId":null,"isActive":true,"createdAt":"2026-01-20 20:11:18.018","updatedAt":"2026-01-20 20:11:18.018"},{"id":"cmkn150ht001rfa9obx88n2q0","level":"L2","code":"BTM","name":"Bottoms","slug":"bottoms","parentId":"cmkn113120017fa9ozk1r0mzh","manufacturingGroup":null,"defaultShippingProfile":null,"defaultSizeProfileId":null,"isActive":true,"createdAt":"2026-01-20 20:11:32.417","updatedAt":"2026-01-20 20:11:32.417"},{"id":"cmkn15g43001tfa9o1avka68u","level":"L2","code":"JAC","name":"Jackets","slug":"jackets","parentId":"cmkn11jfm0019fa9ohfetm6cj","manufacturingGroup":null,"defaultShippingProfile":null,"defaultSizeProfileId":null,"isActive":true,"createdAt":"2026-01-20 20:11:52.659","updatedAt":"2026-01-20 20:11:52.659"},{"id":"cmkn15r8n001vfa9opmx2ww9u","level":"L2","code":"COA","name":"Coats","slug":"coats","parentId":"cmkn11jfm0019fa9ohfetm6cj","manufacturingGroup":null,"defaultShippingProfile":null,"defaultSizeProfileId":null,"isActive":true,"createdAt":"2026-01-20 20:12:07.079","updatedAt":"2026-01-20 20:12:07.079"},{"id":"cmkn16lku001xfa9oectb4oxo","level":"L2","code":"KNT_TOP","name":"Knit Tops","slug":"knit-tops","parentId":"cmkn11svh001bfa9o93hg5b1p","manufacturingGroup":null,"defaultShippingProfile":null,"defaultSizeProfileId":null,"isActive":true,"createdAt":"2026-01-20 20:12:46.398","updatedAt":"2026-01-20 20:12:46.398"},{"id":"cmkn16zd6001zfa9o7ki5yipx","level":"L2","code":"KNT_BOT","name":"Knit Bottoms","slug":"knit-bottoms","parentId":"cmkn11svh001bfa9o93hg5b1p","manufacturingGroup":null,"defaultShippingProfile":null,"defaultSizeProfileId":null,"isActive":true,"createdAt":"2026-01-20 20:13:04.266","updatedAt":"2026-01-20 20:13:04.266"},{"id":"cmkn17fmd0021fa9o37ukxl04","level":"L2","code":"DNM_TOP","name":"Denim Tops","slug":"denim-tops","parentId":"cmkn122ny001dfa9oskogqp3l","manufacturingGroup":null,"defaultShippingProfile":null,"defaultSizeProfileId":null,"isActive":true,"createdAt":"2026-01-20 20:13:25.333","updatedAt":"2026-01-20 20:13:25.333"},{"id":"cmkn17qhk0023fa9oqa3t1exu","level":"L2","code":"DNM_BOT","name":"Denim Bottoms","slug":"denim-bottoms","parentId":"cmkn122ny001dfa9oskogqp3l","manufacturingGroup":null,"defaultShippingProfile":null,"defaultSizeProfileId":null,"isActive":true,"createdAt":"2026-01-20 20:13:39.417","updatedAt":"2026-01-20 20:13:39.417"},{"id":"cmkn18d4g0025fa9o8tyypbbe","level":"L2","code":"LTH_TOPS","name":"Leather Tops","slug":"leather-tops","parentId":"cmkn12bxh001ffa9o4fiqgf9g","manufacturingGroup":null,"defaultShippingProfile":null,"defaultSizeProfileId":null,"isActive":true,"createdAt":"2026-01-20 20:14:08.752","updatedAt":"2026-01-20 20:14:08.752"},{"id":"cmkn18qqt0027fa9oynojdry6","level":"L2","code":"LTH_BOTTOMS","name":"Leather Bottoms","slug":"leather-bottoms","parentId":"cmkn12bxh001ffa9o4fiqgf9g","manufacturingGroup":null,"defaultShippingProfile":null,"defaultSizeProfileId":null,"isActive":true,"createdAt":"2026-01-20 20:14:26.405","updatedAt":"2026-01-20 20:14:26.405"},{"id":"cmkn1acdw0029fa9oqazhi7k7","level":"L2","code":"SHO","name":"Shoes","slug":"shoes","parentId":"cmkn12xrj001jfa9ohp7o8urw","manufacturingGroup":null,"defaultShippingProfile":null,"defaultSizeProfileId":null,"isActive":true,"createdAt":"2026-01-20 20:15:41.109","updatedAt":"2026-01-20 20:15:41.109"},{"id":"cmkn1b9ux002bfa9oh7moq1py","level":"L3","code":"TSH","name":"T-Shirt","slug":"t-shirt","parentId":"cmkn14pdu001pfa9otiivzn1x","manufacturingGroup":"JERSEY","defaultShippingProfile":"LIGHT","defaultSizeProfileId":null,"isActive":true,"createdAt":"2026-01-20 20:16:24.489","updatedAt":"2026-01-20 20:16:24.489"},{"id":"cmkn1bswa002dfa9o3rxhdswu","level":"L3","code":"SHR","name":"Shirt","slug":"shirt","parentId":"cmkn14pdu001pfa9otiivzn1x","manufacturingGroup":"WOVEN","defaultShippingProfile":"LIGHT","defaultSizeProfileId":null,"isActive":true,"createdAt":"2026-01-20 20:16:49.162","updatedAt":"2026-01-20 20:16:49.162"},{"id":"cmkn1cbdi002ffa9o8regnvi0","level":"L3","code":"BLS","name":"Blouse","slug":"blouse","parentId":"cmkn14pdu001pfa9otiivzn1x","manufacturingGroup":"JERSEY","defaultShippingProfile":"LIGHT","defaultSizeProfileId":null,"isActive":true,"createdAt":"2026-01-20 20:17:13.11","updatedAt":"2026-01-20 20:17:13.11"},{"id":"cmkn1cr1v002hfa9o6da28vjf","level":"L3","code":"TNK","name":"Tank Top","slug":"tank-top","parentId":"cmkn14pdu001pfa9otiivzn1x","manufacturingGroup":"WOVEN","defaultShippingProfile":"LIGHT","defaultSizeProfileId":null,"isActive":true,"createdAt":"2026-01-20 20:17:33.427","updatedAt":"2026-01-20 20:17:33.427"},{"id":"cmkn1d695002jfa9omneu17ma","level":"L3","code":"POL","name":"Polo","slug":"polo","parentId":"cmkn14pdu001pfa9otiivzn1x","manufacturingGroup":"WOVEN","defaultShippingProfile":"LIGHT","defaultSizeProfileId":null,"isActive":true,"createdAt":"2026-01-20 20:17:53.129","updatedAt":"2026-01-20 20:17:53.129"},{"id":"cmkn1dy27002lfa9o862m8gj2","level":"L3","code":"PNT","name":"Pants","slug":"pants","parentId":"cmkn150ht001rfa9obx88n2q0","manufacturingGroup":"WOVEN","defaultShippingProfile":"MEDIUM","defaultSizeProfileId":null,"isActive":true,"createdAt":"2026-01-20 20:18:29.167","updatedAt":"2026-01-20 20:18:29.167"},{"id":"cmkn1fwk0002rfa9o321fyifc","level":"L3","code":"SHO","name":"Shorts","slug":"shorts","parentId":"cmkn150ht001rfa9obx88n2q0","manufacturingGroup":"JERSEY","defaultShippingProfile":"LIGHT","defaultSizeProfileId":null,"isActive":true,"createdAt":"2026-01-20 20:20:00.529","updatedAt":"2026-01-20 20:20:00.529"},{"id":"cmkn1gcyg002tfa9omdkd3bc5","level":"L3","code":"SKR","name":"Skirt","slug":"skirt","parentId":"cmkn150ht001rfa9obx88n2q0","manufacturingGroup":"WOVEN","defaultShippingProfile":"LIGHT","defaultSizeProfileId":null,"isActive":true,"createdAt":"2026-01-20 20:20:21.784","updatedAt":"2026-01-20 20:20:21.784"},{"id":"cmkn1gtzh002vfa9opgy3al3m","level":"L3","code":"LGS","name":"Leggings","slug":"leggings","parentId":"cmkn150ht001rfa9obx88n2q0","manufacturingGroup":"WOVEN","defaultShippingProfile":"LIGHT","defaultSizeProfileId":null,"isActive":true,"createdAt":"2026-01-20 20:20:43.853","updatedAt":"2026-01-20 20:20:43.853"},{"id":"cmkn1hq4v002xfa9or7ayuu0m","level":"L3","code":"BLZ","name":"Blazer","slug":"blazer","parentId":"cmkn15g43001tfa9o1avka68u","manufacturingGroup":"WOVEN","defaultShippingProfile":"MEDIUM","defaultSizeProfileId":null,"isActive":true,"createdAt":"2026-01-20 20:21:25.519","updatedAt":"2026-01-20 20:21:25.519"},{"id":"cmkn1i5xw002zfa9o3fwj6bdw","level":"L3","code":"BOJ","name":"Bomber Jacket","slug":"bomber-jacket","parentId":"cmkn15g43001tfa9o1avka68u","manufacturingGroup":"WOVEN","defaultShippingProfile":"MEDIUM","defaultSizeProfileId":null,"isActive":true,"createdAt":"2026-01-20 20:21:46.005","updatedAt":"2026-01-20 20:21:46.005"},{"id":"cmkn1jbtq0031fa9o6h5zq3qe","level":"L3","code":"TRC","name":"Trench Coat","slug":"trench-coat","parentId":"cmkn15r8n001vfa9opmx2ww9u","manufacturingGroup":"WOVEN","defaultShippingProfile":"MEDIUM","defaultSizeProfileId":null,"isActive":true,"createdAt":"2026-01-20 20:22:40.286","updatedAt":"2026-01-20 20:22:40.286"},{"id":"cmkn1jpjj0033fa9ov4du9axu","level":"L3","code":"PUF","name":"Puffer Coat","slug":"puffer-coat","parentId":"cmkn15r8n001vfa9opmx2ww9u","manufacturingGroup":"WOVEN","defaultShippingProfile":"MEDIUM","defaultSizeProfileId":null,"isActive":true,"createdAt":"2026-01-20 20:22:58.063","updatedAt":"2026-01-20 20:22:58.063"},{"id":"cmkn1k35u0035fa9o7du81xfq","level":"L3","code":"WOC","name":"Wool Coat","slug":"wool-coat","parentId":"cmkn15r8n001vfa9opmx2ww9u","manufacturingGroup":"WOVEN","defaultShippingProfile":"MEDIUM","defaultSizeProfileId":null,"isActive":true,"createdAt":"2026-01-20 20:23:15.715","updatedAt":"2026-01-20 20:23:15.715"},{"id":"cmkn1kuah0037fa9oj8jy61k5","level":"L3","code":"SWT","name":"Sweater","slug":"sweater","parentId":"cmkn16lku001xfa9oectb4oxo","manufacturingGroup":"KNITWEAR","defaultShippingProfile":"LIGHT","defaultSizeProfileId":null,"isActive":true,"createdAt":"2026-01-20 20:23:50.874","updatedAt":"2026-01-20 20:23:50.874"},{"id":"cmkn1l7nz0039fa9ozw8svc2i","level":"L3","code":"CAR","name":"Cardigan","slug":"cardigan","parentId":"cmkn16lku001xfa9oectb4oxo","manufacturingGroup":"KNITWEAR","defaultShippingProfile":"LIGHT","defaultSizeProfileId":null,"isActive":true,"createdAt":"2026-01-20 20:24:08.207","updatedAt":"2026-01-20 20:24:08.207"},{"id":"cmkn1llmw003bfa9oelukznpn","level":"L3","code":"KPO","name":"Knit Polo","slug":"knit-polo","parentId":"cmkn16lku001xfa9oectb4oxo","manufacturingGroup":"KNITWEAR","defaultShippingProfile":"LIGHT","defaultSizeProfileId":null,"isActive":true,"createdAt":"2026-01-20 20:24:26.312","updatedAt":"2026-01-20 20:24:26.312"},{"id":"cmkn1m28w003dfa9ojl416rhh","level":"L3","code":"KPN","name":"Knit Pants","slug":"knit-pants","parentId":"cmkn16zd6001zfa9o7ki5yipx","manufacturingGroup":"KNITWEAR","defaultShippingProfile":"LIGHT","defaultSizeProfileId":null,"isActive":true,"createdAt":"2026-01-20 20:24:47.84","updatedAt":"2026-01-20 20:24:47.84"},{"id":"cmkn1meug003ffa9ounhsbyf8","level":"L3","code":"KSK","name":"Knit Skirt","slug":"knit-skirt","parentId":"cmkn16zd6001zfa9o7ki5yipx","manufacturingGroup":"KNITWEAR","defaultShippingProfile":"LIGHT","defaultSizeProfileId":null,"isActive":true,"createdAt":"2026-01-20 20:25:04.169","updatedAt":"2026-01-20 20:25:04.169"},{"id":"cmkn1n5br003hfa9o2xc0b5ik","level":"L3","code":"DSH","name":"Denim Shirt","slug":"denim-shirt","parentId":"cmkn17fmd0021fa9o37ukxl04","manufacturingGroup":"DENIM","defaultShippingProfile":"LIGHT","defaultSizeProfileId":null,"isActive":true,"createdAt":"2026-01-20 20:25:38.488","updatedAt":"2026-01-20 20:25:38.488"},{"id":"cmkn1ni4k003jfa9ozoghaybh","level":"L3","code":"DJA","name":"Denim Jacket","slug":"denim-jacket","parentId":"cmkn17fmd0021fa9o37ukxl04","manufacturingGroup":"DENIM","defaultShippingProfile":"MEDIUM","defaultSizeProfileId":null,"isActive":true,"createdAt":"2026-01-20 20:25:55.077","updatedAt":"2026-01-20 20:25:55.077"},{"id":"cmkn1nyqn003lfa9oae931wed","level":"L3","code":"SJE","name":"Skinny Jeans","slug":"skinny-jeans","parentId":"cmkn17qhk0023fa9oqa3t1exu","manufacturingGroup":"DENIM","defaultShippingProfile":"LIGHT","defaultSizeProfileId":null,"isActive":true,"createdAt":"2026-01-20 20:26:16.608","updatedAt":"2026-01-20 20:26:16.608"},{"id":"cmkn1ofcm003nfa9okwzjc1w4","level":"L3","code":"STJ","name":"Straight Jeans","slug":"straight-jeans","parentId":"cmkn17qhk0023fa9oqa3t1exu","manufacturingGroup":"DENIM","defaultShippingProfile":"MEDIUM","defaultSizeProfileId":null,"isActive":true,"createdAt":"2026-01-20 20:26:38.134","updatedAt":"2026-01-20 20:26:38.134"},{"id":"cmkn1oslo003pfa9oamcqf2du","level":"L3","code":"WJE","name":"Wide Leg Jeans","slug":"wide-leg-jeans","parentId":"cmkn17qhk0023fa9oqa3t1exu","manufacturingGroup":"DENIM","defaultShippingProfile":"MEDIUM","defaultSizeProfileId":null,"isActive":true,"createdAt":"2026-01-20 20:26:55.308","updatedAt":"2026-01-20 20:26:55.308"},{"id":"cmkn1pahb003tfa9o2vjvmy4x","level":"L3","code":"DST","name":"Denim Shorts","slug":"denim-shorts","parentId":"cmkn17qhk0023fa9oqa3t1exu","manufacturingGroup":"DENIM","defaultShippingProfile":"LIGHT","defaultSizeProfileId":null,"isActive":true,"createdAt":"2026-01-20 20:27:18.48","updatedAt":"2026-01-20 20:27:18.48"},{"id":"cmkn1qjny003vfa9o7t3pt3lw","level":"L3","code":"LJAC","name":"Leather Jacket","slug":"leather-jacket","parentId":"cmkn18d4g0025fa9o8tyypbbe","manufacturingGroup":"OUTERWEAR","defaultShippingProfile":"MEDIUM","defaultSizeProfileId":null,"isActive":true,"createdAt":"2026-01-20 20:28:17.038","updatedAt":"2026-01-20 20:28:17.038"},{"id":"cmkn1r7bv003xfa9ojontl1kq","level":"L3","code":"LST","name":"Leather Shirt","slug":"leather-shirt","parentId":"cmkn18d4g0025fa9o8tyypbbe","manufacturingGroup":"OUTERWEAR","defaultShippingProfile":"LIGHT","defaultSizeProfileId":null,"isActive":true,"createdAt":"2026-01-20 20:28:47.707","updatedAt":"2026-01-20 20:28:47.707"},{"id":"cmkn1rq92003zfa9o8ywow2rr","level":"L3","code":"LPN","name":"Leather Pants","slug":"leather-pants","parentId":"cmkn18qqt0027fa9oynojdry6","manufacturingGroup":"OUTERWEAR","defaultShippingProfile":"LIGHT","defaultSizeProfileId":null,"isActive":true,"createdAt":"2026-01-20 20:29:12.23","updatedAt":"2026-01-20 20:29:12.23"},{"id":"cmkn1s4zj0041fa9oaripren9","level":"L3","code":"LSK","name":"Leather Skirt","slug":"leather-skirt","parentId":"cmkn18qqt0027fa9oynojdry6","manufacturingGroup":"OUTERWEAR","defaultShippingProfile":"LIGHT","defaultSizeProfileId":null,"isActive":true,"createdAt":"2026-01-20 20:29:31.328","updatedAt":"2026-01-20 20:29:31.328"},{"id":"cmkn2uacf006bfa9obk5aovrk","level":"L2","code":"FDRS","name":"Dresses","slug":"dresses","parentId":"cmkn14bzx001nfa9oj5xpaawo","manufacturingGroup":null,"defaultShippingProfile":null,"defaultSizeProfileId":null,"isActive":true,"createdAt":"2026-01-20 20:59:11.199","updatedAt":"2026-01-20 20:59:11.199"},{"id":"cmkn2uomm006dfa9oetgfun2t","level":"L2","code":"FSU","name":"Suits","slug":"suits","parentId":"cmkn14bzx001nfa9oj5xpaawo","manufacturingGroup":null,"defaultShippingProfile":null,"defaultSizeProfileId":null,"isActive":true,"createdAt":"2026-01-20 20:59:29.71","updatedAt":"2026-01-20 20:59:29.71"},{"id":"cmkn2vbix006ffa9ozrri523k","level":"L3","code":"MDR","name":"Mini Dress","slug":"mini-dress","parentId":"cmkn2uacf006bfa9obk5aovrk","manufacturingGroup":"WOVEN","defaultShippingProfile":"LIGHT","defaultSizeProfileId":null,"isActive":true,"createdAt":"2026-01-20 20:59:59.385","updatedAt":"2026-01-20 20:59:59.385"},{"id":"cmkn2vo90006hfa9oo9ufmejh","level":"L3","code":"MDD","name":"Midi Dress","slug":"midi-dress","parentId":"cmkn2uacf006bfa9obk5aovrk","manufacturingGroup":"WOVEN","defaultShippingProfile":"LIGHT","defaultSizeProfileId":null,"isActive":true,"createdAt":"2026-01-20 21:00:15.877","updatedAt":"2026-01-20 21:00:15.877"},{"id":"cmkn2w2jz006jfa9oui2v0owy","level":"L3","code":"MXD","name":"Maxi Dress","slug":"maxi-dress","parentId":"cmkn2uacf006bfa9obk5aovrk","manufacturingGroup":"WOVEN","defaultShippingProfile":"MEDIUM","defaultSizeProfileId":null,"isActive":true,"createdAt":"2026-01-20 21:00:34.415","updatedAt":"2026-01-20 21:00:34.415"},{"id":"cmkn2wfb9006lfa9oobb77lxb","level":"L3","code":"EVD","name":"Evening Dress","slug":"evening-dress","parentId":"cmkn2uacf006bfa9obk5aovrk","manufacturingGroup":"WOVEN","defaultShippingProfile":"MEDIUM","defaultSizeProfileId":null,"isActive":true,"createdAt":"2026-01-20 21:00:50.95","updatedAt":"2026-01-20 21:00:50.95"},{"id":"cmkn2wxwv006nfa9ozg2biscm","level":"L3","code":"SST","name":"Suit Set","slug":"suit-set","parentId":"cmkn2uomm006dfa9oetgfun2t","manufacturingGroup":"WOVEN","defaultShippingProfile":"HEAVY","defaultSizeProfileId":null,"isActive":true,"createdAt":"2026-01-20 21:01:15.055","updatedAt":"2026-01-20 21:01:15.055"},{"id":"cmkn2xdd1006pfa9oc4lk8oxs","level":"L3","code":"BSP","name":"Blazer & Pants Set","slug":"blazer-pants-set","parentId":"cmkn2uomm006dfa9oetgfun2t","manufacturingGroup":"WOVEN","defaultShippingProfile":"HEAVY","defaultSizeProfileId":null,"isActive":true,"createdAt":"2026-01-20 21:01:35.078","updatedAt":"2026-01-20 21:01:35.078"},{"id":"cmkn2xq24006rfa9on7jqupxu","level":"L3","code":"TUX","name":"Tuxedo","slug":"tuxedo","parentId":"cmkn2uomm006dfa9oetgfun2t","manufacturingGroup":"JERSEY","defaultShippingProfile":"MEDIUM","defaultSizeProfileId":null,"isActive":true,"createdAt":"2026-01-20 21:01:51.533","updatedAt":"2026-01-20 21:01:51.533"}]